[
  {
    "type": "function",
    "name": "addressToUsername",
    "inputs": [
      { "name": "", "type": "address", "internalType": "address" }
    ],
    "outputs": [
      { "name": "", "type": "string", "internalType": "string" }
    ],
    "stateMutability": "view"
  },
  {
    "type": "function",
    "name": "chanceCardCount",
    "inputs": [
      { "name": "", "type": "string", "internalType": "string" }
    ],
    "outputs": [
      { "name": "", "type": "uint256", "internalType": "uint256" }
    ],
    "stateMutability": "view"
  },
  {
    "type": "function",
    "name": "chanceCards",
    "inputs": [
      { "name": "", "type": "string", "internalType": "string" },
      { "name": "", "type": "uint256", "internalType": "uint256" }
    ],
    "outputs": [
      { "name": "", "type": "string", "internalType": "string" }
    ],
    "stateMutability": "view"
  },
  {
    "type": "function",
    "name": "communityCardCount",
    "inputs": [
      { "name": "", "type": "string", "internalType": "string" }
    ],
    "outputs": [
      { "name": "", "type": "uint256", "internalType": "uint256" }
    ],
    "stateMutability": "view"
  },
  {
    "type": "function",
    "name": "communityCards",
    "inputs": [
      { "name": "", "type": "string", "internalType": "string" },
      { "name": "", "type": "uint256", "internalType": "uint256" }
    ],
    "outputs": [
      { "name": "", "type": "string", "internalType": "string" }
    ],
    "stateMutability": "view"
  },
  {
    "type": "function",
    "name": "createGame",
    "inputs": [
      { "name": "gameType", "type": "uint8", "internalType": "uint8" },
      { "name": "playerSymbol", "type": "uint8", "internalType": "uint8" },
      { "name": "numberOfPlayers", "type": "uint8", "internalType": "uint8" },
      {
        "name": "settings",
        "type": "tuple",
        "internalType": "struct Blockopoly.GameSettings",
        "components": [
          { "name": "maxPlayers", "type": "uint8", "internalType": "uint8" },
          { "name": "privateRoom", "type": "bool", "internalType": "bool" },
          { "name": "auction", "type": "bool", "internalType": "bool" },
          { "name": "rentInPrison", "type": "bool", "internalType": "bool" },
          { "name": "mortgage", "type": "bool", "internalType": "bool" },
          { "name": "evenBuild", "type": "bool", "internalType": "bool" },
          { "name": "startingCash", "type": "uint256", "internalType": "uint256" },
          { "name": "randomizePlayOrder", "type": "bool", "internalType": "bool" }
        ]
      }
    ],
    "outputs": [
      { "name": "", "type": "string", "internalType": "string" }
    ],
    "stateMutability": "nonpayable"
  },
  {
    "type": "function",
    "name": "gamePlayerSymbols",
    "inputs": [
      { "name": "", "type": "string", "internalType": "string" },
      { "name": "", "type": "address", "internalType": "address" }
    ],
    "outputs": [
      { "name": "", "type": "uint8", "internalType": "enum Blockopoly.PlayerSymbol" }
    ],
    "stateMutability": "view"
  },
  {
    "type": "function",
    "name": "gamePlayers",
    "inputs": [
      { "name": "", "type": "string", "internalType": "string" },
      { "name": "", "type": "address", "internalType": "address" }
    ],
    "outputs": [
      { "name": "playerAddress", "type": "address", "internalType": "address" },
      { "name": "gameId", "type": "string", "internalType": "string" },
      { "name": "username", "type": "string", "internalType": "string" },
      { "name": "balance", "type": "uint256", "internalType": "uint256" },
      { "name": "position", "type": "uint8", "internalType": "uint8" },
      { "name": "playerSymbol", "type": "uint8", "internalType": "enum Blockopoly.PlayerSymbol" },
      { "name": "isNext", "type": "bool", "internalType": "bool" }
    ],
    "stateMutability": "view"
  },
  {
    "type": "function",
    "name": "gamePlayersMap",
    "inputs": [
      { "name": "", "type": "string", "internalType": "string" },
      { "name": "", "type": "address", "internalType": "address" }
    ],
    "outputs": [
      { "name": "", "type": "bool", "internalType": "bool" }
    ],
    "stateMutability": "view"
  },
  {
    "type": "function",
    "name": "gameSettings",
    "inputs": [
      { "name": "", "type": "string", "internalType": "string" }
    ],
    "outputs": [
      { "name": "maxPlayers", "type": "uint8", "internalType": "uint8" },
      { "name": "privateRoom", "type": "bool", "internalType": "bool" },
      { "name": "auction", "type": "bool", "internalType": "bool" },
      { "name": "rentInPrison", "type": "bool", "internalType": "bool" },
      { "name": "mortgage", "type": "bool", "internalType": "bool" },
      { "name": "evenBuild", "type": "bool", "internalType": "bool" },
      { "name": "startingCash", "type": "uint256", "internalType": "uint256" },
      { "name": "randomizePlayOrder", "type": "bool", "internalType": "bool" }
    ],
    "stateMutability": "view"
  },
  {
    "type": "function",
    "name": "games",
    "inputs": [
      { "name": "", "type": "string", "internalType": "string" }
    ],
    "outputs": [
      { "name": "id", "type": "string", "internalType": "string" },
      { "name": "status", "type": "uint8", "internalType": "enum Blockopoly.GameStatus" },
      { "name": "nextPlayer", "type": "address", "internalType": "address" },
      { "name": "winner", "type": "address", "internalType": "address" },
      { "name": "createdAt", "type": "uint64", "internalType": "uint64" },
      { "name": "numberOfPlayers", "type": "uint8", "internalType": "uint8" },
      { "name": "endedAt", "type": "uint64", "internalType": "uint64" }
    ],
    "stateMutability": "view"
  },
  {
    "type": "function",
    "name": "getGame",
    "inputs": [
      { "name": "gameId", "type": "string", "internalType": "string" }
    ],
    "outputs": [
      {
        "name": "",
        "type": "tuple",
        "internalType": "struct Blockopoly.Game",
        "components": [
          { "name": "id", "type": "string", "internalType": "string" },
          { "name": "status", "type": "uint8", "internalType": "enum Blockopoly.GameStatus" },
          { "name": "nextPlayer", "type": "address", "internalType": "address" },
          { "name": "winner", "type": "address", "internalType": "address" },
          { "name": "createdAt", "type": "uint64", "internalType": "uint64" },
          { "name": "numberOfPlayers", "type": "uint8", "internalType": "uint8" },
          { "name": "endedAt", "type": "uint64", "internalType": "uint64" }
        ]
      }
    ],
    "stateMutability": "view"
  },
  {
    "type": "function",
    "name": "isRegistered",
    "inputs": [
      { "name": "", "type": "address", "internalType": "address" }
    ],
    "outputs": [
      { "name": "", "type": "bool", "internalType": "bool" }
    ],
    "stateMutability": "view"
  },
  {
    "type": "function",
    "name": "players",
    "inputs": [
      { "name": "", "type": "address", "internalType": "address" }
    ],
    "outputs": [
      { "name": "username", "type": "string", "internalType": "string" },
      { "name": "playerAddress", "type": "address", "internalType": "address" },
      { "name": "timestamp", "type": "uint64", "internalType": "uint64" }
    ],
    "stateMutability": "view"
  },
  {
    "type": "function",
    "name": "propertiesOwnedCount",
    "inputs": [
      { "name": "", "type": "string", "internalType": "string" },
      { "name": "", "type": "address", "internalType": "address" }
    ],
    "outputs": [
      { "name": "", "type": "uint8", "internalType": "uint8" }
    ],
    "stateMutability": "view"
  },
  {
    "type": "function",
    "name": "propertiesOwnedMap",
    "inputs": [
      { "name": "", "type": "string", "internalType": "string" },
      { "name": "", "type": "address", "internalType": "address" },
      { "name": "", "type": "uint8", "internalType": "uint8" }
    ],
    "outputs": [
      { "name": "", "type": "bool", "internalType": "bool" }
    ],
    "stateMutability": "view"
  },
  {
    "type": "function",
    "name": "registerNewPlayer",
    "inputs": [
      { "name": "username", "type": "string", "internalType": "string" }
    ],
    "outputs": [],
    "stateMutability": "nonpayable"
  },
  {
    "type": "function",
    "name": "usedGameIds",
    "inputs": [
      { "name": "", "type": "string", "internalType": "string" }
    ],
    "outputs": [
      { "name": "", "type": "bool", "internalType": "bool" }
    ],
    "stateMutability": "view"
  },
  {
    "type": "function",
    "name": "usernameToAddress",
    "inputs": [
      { "name": "", "type": "string", "internalType": "string" }
    ],
    "outputs": [
      { "name": "", "type": "address", "internalType": "address" }
    ],
    "stateMutability": "view"
  },
  {
    "type": "event",
    "name": "GameCreated",
    "inputs": [
      { "name": "gameId", "type": "string", "indexed": true, "internalType": "string" },
      { "name": "creator", "type": "address", "indexed": true, "internalType": "address" },
      { "name": "timestamp", "type": "uint64", "indexed": false, "internalType": "uint64" }
    ],
    "anonymous": false
  },
  {
    "type": "event",
    "name": "PlayerCreated",
    "inputs": [
      { "name": "username", "type": "string", "indexed": true, "internalType": "string" },
      { "name": "player", "type": "address", "indexed": true, "internalType": "address" },
      { "name": "timestamp", "type": "uint64", "indexed": false, "internalType": "uint64" }
    ],
    "anonymous": false
  }
]
